{
  "$schema": "https://schema.management.azure.com/schemas/2019-04-01/deploymentParameters.json#",
  "contentVersion": "1.0.0.0",
  "parameters": {
    "location": {
      "value": "westeurope"
    },
    "tenantId": {
      "value": null
    },
    "applicationId": {
      "value": null
    },
    "applicationSecret": {
      "value": null
    },
    "azureSovereignCloud": {
      "value": "public"
    },
    "prefix": {
      "value": null
    },
    "virtualMachineSize": {
      "value": null
    },
    "adminUsername": {
      "value": null
    },
    "adminPassword": {
      "value": null
    },
    "ccScriptFilePath": {
      "value": "https://testdevtrawe.blob.core.windows.net/test/initcc.sh?sp=r&st=2022-06-30T22:43:01Z&se=2032-07-01T06:43:01Z&sv=2021-06-08&sr=b&sig=6OXlu9A7GPg0EpT7YgRN20O98LnvJ22Np8dJuzKnHcQ%3D"
    },
    "ccScriptFileName": {
      "value": "initcc.sh"
    }
  }
}
